sunways/__init__.py
sunways/const.py
sunways/exceptions.py
sunways/inverter.py
sunways/modbus.py
sunways/product.py
sunways/protocol.py
sunways/util.py
sunways-1.0.0.dist-info/licenses/LICENSE
sunways-1.0.0.dist-info/METADATA
sunways-1.0.0.dist-info/WHEEL
sunways-1.0.0.dist-info/top_level.txt
sunways-1.0.0.dist-info/RECORD
