Metadata-Version: 2.4
Name: sunways
Version: 1.0.0
Summary: Read data from Sunways inverter via local network
Home-page: https://github.com/chrisleo/sunways
Author: Martin Letenay, Marcel Blijleven
Author-email: chrisleo.yu.cn@gmail.com
License: MIT
Keywords: Sunways,Solar Panel,Inverter,Photovoltaics,PV
Classifier: Development Status :: 5 - Production/Stable
Classifier: Intended Audience :: Developers
Classifier: Topic :: Software Development :: Libraries :: Python Modules
Classifier: License :: OSI Approved :: MIT License
Classifier: Programming Language :: Python :: 3
Classifier: Programming Language :: Python :: 3.8
Classifier: Programming Language :: Python :: 3.9
Classifier: Programming Language :: Python :: 3.10
Classifier: Programming Language :: Python :: 3.11
Classifier: Programming Language :: Python :: 3.12
Classifier: Programming Language :: Python :: 3.13
Requires-Python: >=3.8
License-File: LICENSE
Dynamic: license-file
